taca/__init__.py
taca/cli.py
taca/analysis/__init__.py
taca/analysis/analysis.py
taca/analysis/analysis_nanopore.py
taca/analysis/cli.py
taca/backup/__init__.py
taca/backup/backup.py
taca/backup/cli.py
taca/cleanup/__init__.py
taca/cleanup/cleanup.py
taca/cleanup/cli.py
taca/illumina/HiSeqX_Runs.py
taca/illumina/HiSeq_Runs.py
taca/illumina/MiSeq_Runs.py
taca/illumina/NextSeq_Runs.py
taca/illumina/NovaSeq_Runs.py
taca/illumina/Runs.py
taca/illumina/__init__.py
taca/log/__init__.py
taca/server_status/__init__.py
taca/server_status/cli.py
taca/server_status/cronjobs.py
taca/server_status/server_status.py
taca/testing/__init__.py
taca/testing/cli.py
taca/testing/create_uppmax_like_env.py
taca/utils/__init__.py
taca/utils/bioinfo_tab.py
taca/utils/cli.py
taca/utils/config.py
taca/utils/filesystem.py
taca/utils/minion_barcodes.py
taca/utils/misc.py
taca/utils/statusdb.py
taca/utils/transfer.py
taca-0.9.3.dist-info/LICENSE
taca-0.9.3.dist-info/METADATA
taca-0.9.3.dist-info/WHEEL
taca-0.9.3.dist-info/entry_points.txt
taca-0.9.3.dist-info/top_level.txt
taca-0.9.3.dist-info/RECORD
